[{"xmin":999.0,"ymin":515.5,"xmax":1280.0,"ymax":716.5,"confidence":0.8999023438,"class":7,"name":"truck","is_vehicle":1},{"xmin":1171.0,"ymin":441.0,"xmax":1265.0,"ymax":484.0,"confidence":0.89453125,"class":2,"name":"car","is_vehicle":1},{"xmin":692.0,"ymin":587.0,"xmax":790.0,"ymax":663.0,"confidence":0.8862304688,"class":2,"name":"car","is_vehicle":1},{"xmin":423.5,"ymin":519.5,"xmax":498.0,"ymax":588.5,"confidence":0.8823242188,"class":2,"name":"car","is_vehicle":1},{"xmin":455.0,"ymin":453.75,"xmax":523.5,"ymax":518.5,"confidence":0.869140625,"class":2,"name":"car","is_vehicle":1},{"xmin":1154.0,"ymin":394.75,"xmax":1236.0,"ymax":426.75,"confidence":0.8305664062,"class":2,"name":"car","is_vehicle":1},{"xmin":428.25,"ymin":240.75,"xmax":543.5,"ymax":338.75,"confidence":0.826171875,"class":7,"name":"truck","is_vehicle":1},{"xmin":744.0,"ymin":296.0,"xmax":804.0,"ymax":324.5,"confidence":0.8012695312,"class":2,"name":"car","is_vehicle":1},{"xmin":266.0,"ymin":315.5,"xmax":321.0,"ymax":376.0,"confidence":0.7905273438,"class":7,"name":"truck","is_vehicle":1},{"xmin":394.5,"ymin":265.75,"xmax":508.5,"ymax":351.75,"confidence":0.7880859375,"class":7,"name":"truck","is_vehicle":1},{"xmin":370.5,"ymin":315.25,"xmax":411.5,"ymax":353.75,"confidence":0.759765625,"class":2,"name":"car","is_vehicle":1},{"xmin":436.0,"ymin":375.75,"xmax":490.5,"ymax":429.25,"confidence":0.7294921875,"class":2,"name":"car","is_vehicle":1},{"xmin":201.75,"ymin":257.25,"xmax":233.75,"ymax":283.75,"confidence":0.7192382812,"class":2,"name":"car","is_vehicle":1},{"xmin":1179.0,"ymin":306.25,"xmax":1279.0,"ymax":360.25,"confidence":0.6665039062,"class":7,"name":"truck","is_vehicle":1},{"xmin":799.0,"ymin":411.5,"xmax":896.0,"ymax":491.5,"confidence":0.60546875,"class":7,"name":"truck","is_vehicle":1},{"xmin":689.0,"ymin":251.0,"xmax":746.0,"ymax":285.0,"confidence":0.5859375,"class":7,"name":"truck","is_vehicle":1},{"xmin":265.5,"ymin":238.5,"xmax":295.0,"ymax":258.5,"confidence":0.5849609375,"class":2,"name":"car","is_vehicle":1},{"xmin":151.5,"ymin":284.25,"xmax":178.25,"ymax":319.25,"confidence":0.5708007812,"class":2,"name":"car","is_vehicle":1},{"xmin":1186.0,"ymin":378.0,"xmax":1278.0,"ymax":418.0,"confidence":0.5654296875,"class":2,"name":"car","is_vehicle":1},{"xmin":321.5,"ymin":327.5,"xmax":364.0,"ymax":366.5,"confidence":0.5493164062,"class":2,"name":"car","is_vehicle":1},{"xmin":797.5,"ymin":411.0,"xmax":896.5,"ymax":491.0,"confidence":0.5205078125,"class":2,"name":"car","is_vehicle":1},{"xmin":143.25,"ymin":220.25,"xmax":169.75,"ymax":245.75,"confidence":0.4677734375,"class":2,"name":"car","is_vehicle":1},{"xmin":560.5,"ymin":231.625,"xmax":594.5,"ymax":252.0,"confidence":0.4545898438,"class":2,"name":"car","is_vehicle":1},{"xmin":944.0,"ymin":256.25,"xmax":1009.0,"ymax":275.75,"confidence":0.3952636719,"class":2,"name":"car","is_vehicle":1},{"xmin":411.25,"ymin":151.25,"xmax":458.25,"ymax":182.5,"confidence":0.3818359375,"class":7,"name":"truck","is_vehicle":1},{"xmin":279.0,"ymin":178.75,"xmax":319.0,"ymax":215.75,"confidence":0.3762207031,"class":7,"name":"truck","is_vehicle":1},{"xmin":303.0,"ymin":187.125,"xmax":340.0,"ymax":223.125,"confidence":0.3610839844,"class":7,"name":"truck","is_vehicle":1},{"xmin":162.25,"ymin":204.625,"xmax":186.0,"ymax":223.375,"confidence":0.3359375,"class":2,"name":"car","is_vehicle":1},{"xmin":412.0,"ymin":554.0,"xmax":476.0,"ymax":672.0,"confidence":0.3081054688,"class":2,"name":"car","is_vehicle":1},{"xmin":613.5,"ymin":173.5,"xmax":699.5,"ymax":206.25,"confidence":0.3029785156,"class":7,"name":"truck","is_vehicle":1},{"xmin":775.5,"ymin":227.875,"xmax":813.5,"ymax":246.75,"confidence":0.2846679688,"class":2,"name":"car","is_vehicle":1},{"xmin":181.375,"ymin":106.25,"xmax":195.875,"ymax":120.75,"confidence":0.2790527344,"class":2,"name":"car","is_vehicle":1},{"xmin":446.0,"ymin":646.5,"xmax":572.0,"ymax":718.5,"confidence":0.2736816406,"class":7,"name":"truck","is_vehicle":1},{"xmin":637.5,"ymin":237.5,"xmax":673.5,"ymax":253.0,"confidence":0.2548828125,"class":2,"name":"car","is_vehicle":1}]