[{"xmin":655.5,"ymin":392.0,"xmax":743.5,"ymax":457.0,"confidence":0.8583984375,"class":2,"name":"car","is_vehicle":1},{"xmin":830.0,"ymin":311.75,"xmax":890.0,"ymax":337.75,"confidence":0.8315429688,"class":2,"name":"car","is_vehicle":1},{"xmin":753.5,"ymin":406.5,"xmax":846.5,"ymax":468.5,"confidence":0.8286132812,"class":2,"name":"car","is_vehicle":1},{"xmin":423.0,"ymin":437.0,"xmax":494.5,"ymax":501.0,"confidence":0.8256835938,"class":2,"name":"car","is_vehicle":1},{"xmin":593.0,"ymin":498.0,"xmax":685.0,"ymax":571.0,"confidence":0.8154296875,"class":2,"name":"car","is_vehicle":1},{"xmin":246.375,"ymin":316.5,"xmax":294.0,"ymax":354.0,"confidence":0.8110351562,"class":2,"name":"car","is_vehicle":1},{"xmin":893.0,"ymin":307.5,"xmax":956.0,"ymax":330.0,"confidence":0.8110351562,"class":2,"name":"car","is_vehicle":1},{"xmin":303.0,"ymin":316.25,"xmax":354.0,"ymax":353.25,"confidence":0.759765625,"class":2,"name":"car","is_vehicle":1},{"xmin":1040.0,"ymin":342.5,"xmax":1114.0,"ymax":371.5,"confidence":0.744140625,"class":2,"name":"car","is_vehicle":1},{"xmin":708.0,"ymin":286.25,"xmax":755.0,"ymax":305.75,"confidence":0.6596679688,"class":2,"name":"car","is_vehicle":1},{"xmin":565.0,"ymin":633.0,"xmax":781.0,"ymax":716.0,"confidence":0.5942382812,"class":5,"name":"bus","is_vehicle":1},{"xmin":447.75,"ymin":557.5,"xmax":569.5,"ymax":675.5,"confidence":0.59375,"class":2,"name":"car","is_vehicle":1},{"xmin":432.25,"ymin":255.25,"xmax":480.25,"ymax":282.75,"confidence":0.5859375,"class":2,"name":"car","is_vehicle":1},{"xmin":266.5,"ymin":556.5,"xmax":337.0,"ymax":634.5,"confidence":0.5756835938,"class":2,"name":"car","is_vehicle":1},{"xmin":156.125,"ymin":260.75,"xmax":189.875,"ymax":288.25,"confidence":0.3688964844,"class":2,"name":"car","is_vehicle":1},{"xmin":390.75,"ymin":129.875,"xmax":429.25,"ymax":141.375,"confidence":0.3605957031,"class":2,"name":"car","is_vehicle":1},{"xmin":362.75,"ymin":150.375,"xmax":385.25,"ymax":164.875,"confidence":0.3420410156,"class":2,"name":"car","is_vehicle":1},{"xmin":192.375,"ymin":179.0,"xmax":214.375,"ymax":198.0,"confidence":0.283203125,"class":2,"name":"car","is_vehicle":1},{"xmin":195.875,"ymin":197.125,"xmax":230.375,"ymax":227.375,"confidence":0.2751464844,"class":2,"name":"car","is_vehicle":1}]