[{"xmin":1088.0,"ymin":395.25,"xmax":1174.0,"ymax":432.75,"confidence":0.892578125,"class":2,"name":"car","is_vehicle":1},{"xmin":246.5,"ymin":382.25,"xmax":337.5,"ymax":481.75,"confidence":0.8720703125,"class":7,"name":"truck","is_vehicle":1},{"xmin":1049.0,"ymin":359.25,"xmax":1133.0,"ymax":394.75,"confidence":0.8583984375,"class":2,"name":"car","is_vehicle":1},{"xmin":701.5,"ymin":238.75,"xmax":842.5,"ymax":317.75,"confidence":0.8505859375,"class":7,"name":"truck","is_vehicle":1},{"xmin":1202.0,"ymin":351.25,"xmax":1280.0,"ymax":382.75,"confidence":0.8017578125,"class":2,"name":"car","is_vehicle":1},{"xmin":544.5,"ymin":309.0,"xmax":591.5,"ymax":338.5,"confidence":0.7861328125,"class":2,"name":"car","is_vehicle":1},{"xmin":962.0,"ymin":371.75,"xmax":1047.0,"ymax":407.25,"confidence":0.7856445312,"class":2,"name":"car","is_vehicle":1},{"xmin":355.0,"ymin":209.0,"xmax":447.5,"ymax":290.0,"confidence":0.767578125,"class":7,"name":"truck","is_vehicle":1},{"xmin":1107.0,"ymin":312.5,"xmax":1171.0,"ymax":336.0,"confidence":0.7670898438,"class":2,"name":"car","is_vehicle":1},{"xmin":117.125,"ymin":242.0,"xmax":143.625,"ymax":264.0,"confidence":0.6674804688,"class":2,"name":"car","is_vehicle":1},{"xmin":1216.0,"ymin":612.5,"xmax":1280.0,"ymax":713.5,"confidence":0.6044921875,"class":2,"name":"car","is_vehicle":1},{"xmin":992.0,"ymin":284.25,"xmax":1047.0,"ymax":305.75,"confidence":0.587890625,"class":2,"name":"car","is_vehicle":1},{"xmin":282.0,"ymin":248.5,"xmax":338.5,"ymax":293.0,"confidence":0.580078125,"class":7,"name":"truck","is_vehicle":1},{"xmin":197.375,"ymin":219.5,"xmax":227.625,"ymax":239.5,"confidence":0.5356445312,"class":2,"name":"car","is_vehicle":1},{"xmin":209.0,"ymin":266.25,"xmax":245.5,"ymax":296.75,"confidence":0.4680175781,"class":2,"name":"car","is_vehicle":1},{"xmin":157.75,"ymin":162.875,"xmax":177.25,"ymax":180.125,"confidence":0.447265625,"class":2,"name":"car","is_vehicle":1},{"xmin":829.5,"ymin":254.25,"xmax":875.5,"ymax":273.75,"confidence":0.4323730469,"class":2,"name":"car","is_vehicle":1},{"xmin":320.75,"ymin":233.25,"xmax":354.25,"ymax":259.75,"confidence":0.4289550781,"class":2,"name":"car","is_vehicle":1},{"xmin":208.75,"ymin":266.0,"xmax":245.75,"ymax":296.5,"confidence":0.3967285156,"class":7,"name":"truck","is_vehicle":1},{"xmin":289.25,"ymin":175.625,"xmax":314.25,"ymax":194.875,"confidence":0.3942871094,"class":2,"name":"car","is_vehicle":1},{"xmin":771.0,"ymin":224.125,"xmax":806.0,"ymax":237.0,"confidence":0.3425292969,"class":2,"name":"car","is_vehicle":1},{"xmin":655.0,"ymin":271.5,"xmax":694.0,"ymax":287.0,"confidence":0.3256835938,"class":2,"name":"car","is_vehicle":1},{"xmin":225.0,"ymin":208.625,"xmax":247.75,"ymax":227.125,"confidence":0.3051757812,"class":2,"name":"car","is_vehicle":1}]