[{"xmin":828.0,"ymin":407.75,"xmax":886.0,"ymax":449.25,"confidence":0.8618164062,"class":2,"name":"car","is_vehicle":1},{"xmin":711.5,"ymin":497.5,"xmax":796.5,"ymax":558.5,"confidence":0.8598632812,"class":2,"name":"car","is_vehicle":1},{"xmin":1003.0,"ymin":203.75,"xmax":1067.0,"ymax":273.75,"confidence":0.8471679688,"class":7,"name":"truck","is_vehicle":1},{"xmin":33.3125,"ymin":413.75,"xmax":143.0,"ymax":466.25,"confidence":0.6791992188,"class":2,"name":"car","is_vehicle":1},{"xmin":589.5,"ymin":243.75,"xmax":636.5,"ymax":268.25,"confidence":0.6313476562,"class":2,"name":"car","is_vehicle":1},{"xmin":962.0,"ymin":171.875,"xmax":991.0,"ymax":187.375,"confidence":0.564453125,"class":2,"name":"car","is_vehicle":1},{"xmin":515.5,"ymin":300.75,"xmax":594.5,"ymax":335.25,"confidence":0.4477539062,"class":2,"name":"car","is_vehicle":1},{"xmin":1009.0,"ymin":153.0,"xmax":1031.0,"ymax":176.0,"confidence":0.4411621094,"class":2,"name":"car","is_vehicle":1},{"xmin":1113.0,"ymin":148.5,"xmax":1135.0,"ymax":163.0,"confidence":0.3952636719,"class":2,"name":"car","is_vehicle":1},{"xmin":72.125,"ymin":297.5,"xmax":328.5,"ymax":412.5,"confidence":0.3369140625,"class":5,"name":"bus","is_vehicle":1},{"xmin":503.75,"ymin":217.0,"xmax":545.0,"ymax":240.5,"confidence":0.3239746094,"class":2,"name":"car","is_vehicle":1},{"xmin":499.0,"ymin":308.25,"xmax":547.0,"ymax":330.25,"confidence":0.2526855469,"class":2,"name":"car","is_vehicle":1}]