[{"xmin":1058.0,"ymin":606.0,"xmax":1208.0,"ymax":709.0,"confidence":0.9287109375,"class":2,"name":"car","is_vehicle":1},{"xmin":788.5,"ymin":423.0,"xmax":864.5,"ymax":470.5,"confidence":0.8959960938,"class":2,"name":"car","is_vehicle":1},{"xmin":1081.0,"ymin":405.75,"xmax":1171.0,"ymax":443.75,"confidence":0.8793945312,"class":2,"name":"car","is_vehicle":1},{"xmin":595.0,"ymin":330.0,"xmax":643.0,"ymax":361.0,"confidence":0.8276367188,"class":2,"name":"car","is_vehicle":1},{"xmin":616.5,"ymin":248.75,"xmax":654.5,"ymax":267.75,"confidence":0.7895507812,"class":2,"name":"car","is_vehicle":1},{"xmin":1220.0,"ymin":426.25,"xmax":1280.0,"ymax":474.75,"confidence":0.77734375,"class":2,"name":"car","is_vehicle":1},{"xmin":277.5,"ymin":289.25,"xmax":320.0,"ymax":314.25,"confidence":0.73046875,"class":2,"name":"car","is_vehicle":1},{"xmin":232.25,"ymin":282.75,"xmax":272.25,"ymax":318.75,"confidence":0.7299804688,"class":2,"name":"car","is_vehicle":1},{"xmin":239.375,"ymin":387.25,"xmax":290.5,"ymax":430.75,"confidence":0.7211914062,"class":2,"name":"car","is_vehicle":1},{"xmin":447.25,"ymin":272.5,"xmax":487.75,"ymax":298.5,"confidence":0.7211914062,"class":2,"name":"car","is_vehicle":1},{"xmin":585.0,"ymin":197.25,"xmax":693.0,"ymax":248.5,"confidence":0.7119140625,"class":7,"name":"truck","is_vehicle":1},{"xmin":290.0,"ymin":173.25,"xmax":344.5,"ymax":224.75,"confidence":0.7075195312,"class":7,"name":"truck","is_vehicle":1},{"xmin":469.5,"ymin":417.5,"xmax":724.5,"ymax":666.5,"confidence":0.671875,"class":5,"name":"bus","is_vehicle":1},{"xmin":664.0,"ymin":247.75,"xmax":704.0,"ymax":270.25,"confidence":0.6069335938,"class":2,"name":"car","is_vehicle":1},{"xmin":211.875,"ymin":223.375,"xmax":241.625,"ymax":245.5,"confidence":0.5786132812,"class":2,"name":"car","is_vehicle":1},{"xmin":500.0,"ymin":622.0,"xmax":801.0,"ymax":716.0,"confidence":0.5517578125,"class":7,"name":"truck","is_vehicle":1},{"xmin":219.75,"ymin":141.25,"xmax":262.0,"ymax":185.5,"confidence":0.5458984375,"class":7,"name":"truck","is_vehicle":1},{"xmin":152.375,"ymin":230.75,"xmax":179.625,"ymax":258.25,"confidence":0.4826660156,"class":2,"name":"car","is_vehicle":1},{"xmin":191.5,"ymin":303.5,"xmax":233.25,"ymax":330.5,"confidence":0.3833007812,"class":2,"name":"car","is_vehicle":1},{"xmin":135.375,"ymin":146.125,"xmax":156.625,"ymax":175.875,"confidence":0.3720703125,"class":7,"name":"truck","is_vehicle":1},{"xmin":429.25,"ymin":164.75,"xmax":463.75,"ymax":187.75,"confidence":0.3422851562,"class":2,"name":"car","is_vehicle":1},{"xmin":170.625,"ymin":171.75,"xmax":194.125,"ymax":185.25,"confidence":0.3298339844,"class":2,"name":"car","is_vehicle":1},{"xmin":135.25,"ymin":211.375,"xmax":162.25,"ymax":229.875,"confidence":0.2946777344,"class":2,"name":"car","is_vehicle":1},{"xmin":181.75,"ymin":111.5,"xmax":206.75,"ymax":137.25,"confidence":0.2578125,"class":7,"name":"truck","is_vehicle":1}]